rag_llama3/ChatWindow.py
rag_llama3/RAG.py
rag_llama3/TextExtractor.py
rag_llama3/VectorDB.py
rag_llama3/__init__.py
rag_llama3/main.py
rag_llama3/preprocess_text.py
rag_llama3-0.1.4.1.dist-info/LICENSE
rag_llama3-0.1.4.1.dist-info/METADATA
rag_llama3-0.1.4.1.dist-info/WHEEL
rag_llama3-0.1.4.1.dist-info/entry_points.txt
rag_llama3-0.1.4.1.dist-info/top_level.txt
rag_llama3-0.1.4.1.dist-info/RECORD
