Metadata-Version: 2.1
Name: rag_llama3
Version: 0.1.4.1
Summary: This repository contains a project that implements a Retrieval-Augmented Generation (RAG) system using the LLaMA3 model. The project focuses on creating embeddings for instructions of a professional bioinformatic software to help users conduct biology research.
Home-page: https://github.com/DNALinux/ai
Author: Songlin Zhao
Author-email: tagorezhao@berkeley.edu
Classifier: Development Status :: 4 - Beta
Classifier: Intended Audience :: Developers
Classifier: Topic :: Software Development :: Build Tools
Classifier: Programming Language :: Python :: 3
Classifier: License :: OSI Approved :: GNU General Public License (GPL)
Classifier: Operating System :: OS Independent
Requires-Python: >=3.10.0, <4
License-File: LICENSE
Requires-Dist: ollama ==0.2.1
Requires-Dist: numpy
Requires-Dist: chromadb ==0.5.3
Requires-Dist: pypdf ==4.2.0
Requires-Dist: beautifulsoup4 ==4.12.2
Requires-Dist: nltk ==3.6.2
Requires-Dist: langchain-community ==0.2.6
